COPYING
COPYING.lesser
MANIFEST.in
NOTICE
README.md
requirements.txt
setup.py
Pyrosex.egg-info/PKG-INFO
Pyrosex.egg-info/SOURCES.txt
Pyrosex.egg-info/dependency_links.txt
Pyrosex.egg-info/not-zip-safe
Pyrosex.egg-info/requires.txt
Pyrosex.egg-info/top_level.txt
compiler/__init__.py
compiler/api/__init__.py
compiler/api/compiler.py
compiler/api/source/auth_key.tl
compiler/api/source/main_api.tl
compiler/api/source/sys_msgs.tl
compiler/api/template/combinator.txt
compiler/api/template/type.txt
compiler/docs/__init__.py
compiler/docs/compiler.py
compiler/docs/template/page.txt
compiler/docs/template/toctree.txt
compiler/errors/__init__.py
compiler/errors/compiler.py
compiler/errors/sort.py
compiler/errors/source/303_SEE_OTHER.tsv
compiler/errors/source/400_BAD_REQUEST.tsv
compiler/errors/source/401_UNAUTHORIZED.tsv
compiler/errors/source/403_FORBIDDEN.tsv
compiler/errors/source/406_NOT_ACCEPTABLE.tsv
compiler/errors/source/420_FLOOD.tsv
compiler/errors/source/500_INTERNAL_SERVER_ERROR.tsv
compiler/errors/source/503_SERVICE_UNAVAILABLE.tsv
compiler/errors/template/class.txt
compiler/errors/template/sub_class.txt
pyrosex/__init__.py
pyrosex/client.py
pyrosex/dispatcher.py
pyrosex/emoji.py
pyrosex/file_id.py
pyrosex/filters.py
pyrosex/mime_types.py
pyrosex/py.typed
pyrosex/sync.py
pyrosex/utils.py
pyrosex/connection/__init__.py
pyrosex/connection/connection.py
pyrosex/connection/transport/__init__.py
pyrosex/connection/transport/tcp/__init__.py
pyrosex/connection/transport/tcp/tcp.py
pyrosex/connection/transport/tcp/tcp_abridged.py
pyrosex/connection/transport/tcp/tcp_abridged_o.py
pyrosex/connection/transport/tcp/tcp_full.py
pyrosex/connection/transport/tcp/tcp_intermediate.py
pyrosex/connection/transport/tcp/tcp_intermediate_o.py
pyrosex/crypto/__init__.py
pyrosex/crypto/aes.py
pyrosex/crypto/mtproto.py
pyrosex/crypto/prime.py
pyrosex/crypto/rsa.py
pyrosex/enums/__init__.py
pyrosex/enums/auto_name.py
pyrosex/enums/chat_action.py
pyrosex/enums/chat_event_action.py
pyrosex/enums/chat_member_status.py
pyrosex/enums/chat_members_filter.py
pyrosex/enums/chat_type.py
pyrosex/enums/message_entity_type.py
pyrosex/enums/message_media_type.py
